{
  "manifest": {
    "publishingInformation": {
      "locales": {
        "en-US": {
          "summary": "MTA Subway Schedules",
          "examplePhrases": [
            "Alexa, ask the subway when the next Queens train is",
            "ask the subway when is the next Manhattan train",
            "help"
          ],
          "name": "mta-subway-schedule",
          "description": "Get the schedules for Manhattan/Queens bound trains on the N/W Broadway stop"
        }
      },
      "isAvailableWorldwide": true,
      "testingInstructions": "Ask when the next Queens or Manhattan trains are",
      "category": "PUBLIC_TRANSPORTATION",
      "distributionCountries": []
    },
    "apis": {
      "custom": {
        "endpoint": {
          "sourceDir": "lambda/custom",
          "uri": "ask-custom-mta-subway-schedule-default"
        }
      }
    },
    "manifestVersion": "1.0"
  }
}
